pytest_listener.py
pytest_listener-1.8.1.dist-info/LICENSE
pytest_listener-1.8.1.dist-info/METADATA
pytest_listener-1.8.1.dist-info/WHEEL
pytest_listener-1.8.1.dist-info/entry_points.txt
pytest_listener-1.8.1.dist-info/top_level.txt
pytest_listener-1.8.1.dist-info/RECORD
