Metadata-Version: 2.1
Name: pytest-listener
Version: 1.8.1
Summary: A simple network listener
Home-page: https://github.com/man-group/pytest-plugins
Author: Tim Couper
Author-email: drtimcouper@gmail.com
License: MIT license
Platform: unix
Platform: linux
Classifier: License :: OSI Approved :: MIT License
Classifier: Development Status :: 5 - Production/Stable
Classifier: Topic :: Software Development :: Libraries
Classifier: Topic :: Software Development :: Testing
Classifier: Topic :: Utilities
Classifier: Intended Audience :: Developers
Classifier: Operating System :: POSIX
Classifier: Operating System :: Microsoft :: Windows
Classifier: Programming Language :: Python :: 3.6
Classifier: Programming Language :: Python :: 3.7
Requires-Python: >=3.6
License-File: LICENSE
Requires-Dist: six
Requires-Dist: pytest
Requires-Dist: pytest-server-fixtures
